pwmaker/__init__.py
pwmaker/pwmaker.py
pwmaker-1.0.0.dist-info/LICENSE
pwmaker-1.0.0.dist-info/METADATA
pwmaker-1.0.0.dist-info/WHEEL
pwmaker-1.0.0.dist-info/entry_points.txt
pwmaker-1.0.0.dist-info/top_level.txt
pwmaker-1.0.0.dist-info/RECORD
