Metadata-Version: 2.1
Name: pwmaker
Version: 1.0.0
Summary: Generate a strong and random password with variable length through the command line interface
Author-email: Aleksandar Gjorgjevski <aleksandarski@yandex.com>
License: Copyright (c) 2023 Aleksandar Gjorgjevski
Project-URL: Source, https://github.com/kolo-vrat/pwmaker
Keywords: Password generator
Classifier: Environment :: Console
Classifier: License :: OSI Approved :: MIT License
Classifier: Programming Language :: Python
Classifier: Programming Language :: Python :: 3 :: Only
Requires-Python: >=3.10
License-File: LICENSE
Provides-Extra: test
Requires-Dist: pytest >=7.4 ; extra == 'test'
